Metadata-Version: 2.1
Name: odoo11-addon-l10n_it_fatturapa_pec
Version: 11.0.1.7.2.99.dev5
Summary: Invio fatture elettroniche tramite PEC
Home-page: https://github.com/OCA/l10n-italy/tree/11.0/l10n_it_fatturapa_pec
Author: Openforce Srls Unipersonale, Odoo Community Association (OCA)
Author-email: support@odoo-community.org
License: LGPL-3
Classifier: Programming Language :: Python
Classifier: Framework :: Odoo
Classifier: Framework :: Odoo :: 11.0
Classifier: License :: OSI Approved :: GNU Lesser General Public License v3 (LGPLv3)
Requires-Python: >=2.7, !=3.0.*, !=3.1.*, !=3.2.*, !=3.3.*, !=3.4.*
Requires-Dist: odoo11-addon-l10n-it-fatturapa-in
Requires-Dist: odoo11-addon-l10n-it-fatturapa-out
Requires-Dist: odoo11-addon-l10n-it-sdi-channel
Requires-Dist: odoo <11.1dev,>=11.0a
